[
  {
    "label": "Star",
    "data": {
      "quartiles": [
        0.0,
        0.0,
        0.0,
        0.000038711348817308536,
        0.0013738367159361075
      ],
      "mean": 0.00004782510480445046
    }
  },
  {
    "label": "Bucklin",
    "data": {
      "quartiles": [
        0.0,
        0.0,
        1.8112280478987943e-7,
        0.00010602103422851171,
        0.0011926907629769801
      ],
      "mean": 0.00007398116391334127
    }
  },
  {
    "label": "Black",
    "data": {
      "quartiles": [
        0.0,
        0.0,
        0.0,
        0.00003695134062283501,
        0.0012282917076234412
      ],
      "mean": 0.00004742005530065379
    }
  },
  {
    "label": "Copeland",
    "data": {
      "quartiles": [
        0.0,
        0.0,
        0.0,
        0.0000341675536572339,
        0.0015178714799152714
      ],
      "mean": 0.0000463000543846183
    }
  },
  {
    "label": "Ranked Choice Most Last",
    "data": {
      "quartiles": [
        0.0,
        0.0,
        0.000030045615147180625,
        0.00017284351512977025,
        0.0027329809128806915
      ],
      "mean": 0.00012454059422853893
    }
  },
  {
    "label": "Ranked Choice Fewest First",
    "data": {
      "quartiles": [
        0.0,
        0.0,
        0.0,
        0.00003563373367473588,
        0.0017050448078819614
      ],
      "mean": 0.000056949807014768915
    }
  },
  {
    "label": "Condorcet Ranked Pairs",
    "data": {
      "quartiles": [
        0.0,
        0.0,
        0.0,
        0.00003054937225032361,
        0.0014673481603733052
      ],
      "mean": 0.00004547241917962176
    }
  },
  {
    "label": "Condorcet Least Reversal",
    "data": {
      "quartiles": [
        0.0,
        0.0,
        0.0,
        0.000035666501457516374,
        0.001472755770062264
      ],
      "mean": 0.00004898464356156868
    }
  },
  {
    "label": "Plurality + runoff",
    "data": {
      "quartiles": [
        0.0,
        0.0,
        0.0,
        0.00003633888340726088,
        0.0013683618352142446
      ],
      "mean": 0.00005676008188787812
    }
  }
]