[
  {
    "label": "Star",
    "data": {
      "quartiles": [
        0.0,
        0.0,
        0.0,
        0.004632494021721545,
        0.04595997085441375
      ],
      "mean": 0.0032510839447048297
    }
  },
  {
    "label": "Bucklin",
    "data": {
      "quartiles": [
        0.0,
        0.0,
        0.0016467556874782475,
        0.007642506662376416,
        0.06737338318619678
      ],
      "mean": 0.005110680299797851
    }
  },
  {
    "label": "Black",
    "data": {
      "quartiles": [
        0.0,
        0.0,
        0.0005752972274244072,
        0.006738965623596549,
        0.07979014726002034
      ],
      "mean": 0.004647126260190646
    }
  },
  {
    "label": "Copeland",
    "data": {
      "quartiles": [
        0.0,
        0.0,
        0.0006528415413317745,
        0.007067030893753205,
        0.09081188812768652
      ],
      "mean": 0.004908786848059056
    }
  },
  {
    "label": "Single Transferable Most Last",
    "data": {
      "quartiles": [
        0.0,
        0.0,
        0.0022399322553494725,
        0.008850451632142473,
        0.07971164955209296
      ],
      "mean": 0.005900198706047275
    }
  },
  {
    "label": "Single Transferable Fewest First",
    "data": {
      "quartiles": [
        0.0,
        0.0,
        0.0032080753831178655,
        0.010657431266649038,
        0.0831337468893846
      ],
      "mean": 0.006947815589394849
    }
  },
  {
    "label": "Condorcet Ranked Pairs",
    "data": {
      "quartiles": [
        0.0,
        0.0,
        0.0010933335941299303,
        0.007878405977091791,
        0.08105880494574315
      ],
      "mean": 0.0053115558644471995
    }
  },
  {
    "label": "Condorcet Least Reversal",
    "data": {
      "quartiles": [
        0.0,
        0.0,
        0.0010229196609270374,
        0.007482613433265204,
        0.07507977667327217
      ],
      "mean": 0.005236593376062059
    }
  },
  {
    "label": "Plurality + runoff",
    "data": {
      "quartiles": [
        0.0,
        0.0,
        0.0032690415205801314,
        0.01093696658066321,
        0.10069061326363872
      ],
      "mean": 0.007114551068961178
    }
  }
]