[
  {
    "label": "Star",
    "data": {
      "quartiles": [
        0.0,
        0.0,
        0.0,
        0.00838327182369726,
        0.0741815880671706
      ],
      "mean": 0.005784068445298175
    }
  },
  {
    "label": "Bucklin",
    "data": {
      "quartiles": [
        0.0,
        0.0,
        0.0,
        0.014706222450640497,
        0.1074259101996411
      ],
      "mean": 0.009176981393432815
    }
  },
  {
    "label": "Black",
    "data": {
      "quartiles": [
        0.0,
        0.0,
        0.0,
        0.014927840432403024,
        0.10022211834620656
      ],
      "mean": 0.009232071720949798
    }
  },
  {
    "label": "Copeland",
    "data": {
      "quartiles": [
        0.0,
        0.0,
        0.0,
        0.014112564055217191,
        0.11086364817400479
      ],
      "mean": 0.008866996881011936
    }
  },
  {
    "label": "Single Transferable Most Last",
    "data": {
      "quartiles": [
        0.0,
        0.0031735390077620804,
        0.02039568210964436,
        0.038696072907636124,
        0.12437455019229816
      ],
      "mean": 0.02406357261236372
    }
  },
  {
    "label": "Single Transferable Fewest First",
    "data": {
      "quartiles": [
        0.0,
        0.0,
        0.0,
        0.013925761232044653,
        0.09202586094823147
      ],
      "mean": 0.008620900824399733
    }
  },
  {
    "label": "Condorcet Ranked Pairs",
    "data": {
      "quartiles": [
        0.0,
        0.0,
        0.0,
        0.014103617766347564,
        0.09013083895481806
      ],
      "mean": 0.008768271316808128
    }
  },
  {
    "label": "Condorcet Least Reversal",
    "data": {
      "quartiles": [
        0.0,
        0.0,
        0.0,
        0.014211198577728547,
        0.12246044257133334
      ],
      "mean": 0.008789419685981337
    }
  },
  {
    "label": "Plurality + runoff",
    "data": {
      "quartiles": [
        0.0,
        0.0,
        0.0,
        0.013184222594556481,
        0.09238418150241585
      ],
      "mean": 0.008292441114553059
    }
  }
]