[
  {
    "label": "Star",
    "data": {
      "quartiles": [
        -0.012166825,
        0.0,
        0.0,
        0.008111216,
        0.020278042
      ],
      "mean": 0.0058314307
    }
  },
  {
    "label": "Bucklin",
    "data": {
      "quartiles": [
        -0.05634058,
        0.0,
        0.0198537,
        0.037560385,
        0.09390096
      ],
      "mean": 0.022702869
    }
  },
  {
    "label": "Black",
    "data": {
      "quartiles": [
        -0.014817615,
        0.0,
        0.0,
        0.00987841,
        0.024696026
      ],
      "mean": 0.0069326255
    }
  },
  {
    "label": "Copeland",
    "data": {
      "quartiles": [
        -0.012658966,
        0.0,
        0.0,
        0.008439311,
        0.021098277
      ],
      "mean": 0.0066310083
    }
  },
  {
    "label": "Single Transferable Most Last",
    "data": {
      "quartiles": [
        -0.024028542,
        0.020193089,
        0.03403399,
        0.049674176,
        0.09389581
      ],
      "mean": 0.03611496
    }
  },
  {
    "label": "Single Transferable Fewest First",
    "data": {
      "quartiles": [
        -0.0025032922,
        0.0,
        0.0,
        0.0016688615,
        0.004172154
      ],
      "mean": 0.0032425232
    }
  },
  {
    "label": "Condorcet Ranked Pairs",
    "data": {
      "quartiles": [
        -0.014147085,
        0.0,
        0.0,
        0.00943139,
        0.023578476
      ],
      "mean": 0.006991423
    }
  },
  {
    "label": "Condorcet Least Reversal",
    "data": {
      "quartiles": [
        -0.013883764,
        0.0,
        0.0,
        0.009255842,
        0.023139605
      ],
      "mean": 0.0069605545
    }
  },
  {
    "label": "Plurality + runoff",
    "data": {
      "quartiles": [
        -0.0027348918,
        0.0,
        0.0,
        0.0018232611,
        0.004558153
      ],
      "mean": 0.0032331413
    }
  }
]