[
  {
    "label": "Dabagh",
    "data": {
      "quartiles": [
        -0.0053395727,
        0.0,
        0.0,
        0.003559715,
        0.008899287
      ],
      "mean": 0.00400275
    }
  },
  {
    "label": "Borda",
    "data": {
      "quartiles": [
        -0.00924553,
        0.0,
        0.0,
        0.0061636865,
        0.015409216
      ],
      "mean": 0.005390183
    }
  },
  {
    "label": "Bullet",
    "data": {
      "quartiles": [
        -0.024667224,
        0.023947185,
        0.038691994,
        0.056356788,
        0.1049712
      ],
      "mean": 0.04130907
    }
  },
  {
    "label": "Plurality",
    "data": {
      "quartiles": [
        -0.009868234,
        0.0,
        0.0,
        0.006578823,
        0.016447058
      ],
      "mean": 0.005217718
    }
  },
  {
    "label": "Approval",
    "data": {
      "quartiles": [
        -0.008056116,
        0.0,
        0.0,
        0.0053707445,
        0.013426861
      ],
      "mean": 0.0049363226
    }
  },
  {
    "label": "Range",
    "data": {
      "quartiles": [
        -0.0019046271,
        0.0,
        0.0,
        0.0012697513,
        0.0031743785
      ],
      "mean": 0.0031257719
    }
  }
]