[
  {
    "label": "Star",
    "data": {
      "quartiles": [
        0.0,
        0.0,
        0.0,
        0.007099312433383549,
        0.08866455808504065
      ],
      "mean": 0.005699276846327358
    }
  },
  {
    "label": "Bucklin",
    "data": {
      "quartiles": [
        0.0,
        0.0,
        0.0,
        0.006907746987902889,
        0.11430576063489334
      ],
      "mean": 0.006862598195540667
    }
  },
  {
    "label": "Black",
    "data": {
      "quartiles": [
        0.0,
        0.0,
        0.0,
        0.007682456408157829,
        0.11288146196373276
      ],
      "mean": 0.006995460764423589
    }
  },
  {
    "label": "Copeland",
    "data": {
      "quartiles": [
        0.0,
        0.0,
        0.0,
        0.006236418229881285,
        0.09812960491055776
      ],
      "mean": 0.006129636003943037
    }
  },
  {
    "label": "Single Transferable Most Last",
    "data": {
      "quartiles": [
        0.00047730115954131236,
        0.022680267021050023,
        0.03612214439295919,
        0.051785773725543896,
        0.13894050941505334
      ],
      "mean": 0.03865332738805087
    }
  },
  {
    "label": "Single Transferable Fewest First",
    "data": {
      "quartiles": [
        0.0,
        0.0,
        0.0,
        0.0016974852979286935,
        0.06680740209483417
      ],
      "mean": 0.0032781748749554944
    }
  },
  {
    "label": "Condorcet Ranked Pairs",
    "data": {
      "quartiles": [
        0.0,
        0.0,
        0.0,
        0.0032587465855867847,
        0.11294438330858426
      ],
      "mean": 0.004687166287872288
    }
  },
  {
    "label": "Condorcet Least Reversal",
    "data": {
      "quartiles": [
        0.0,
        0.0,
        0.0,
        0.0034884189759511134,
        0.10328447431226515
      ],
      "mean": 0.004552777735107133
    }
  },
  {
    "label": "Plurality + runoff",
    "data": {
      "quartiles": [
        0.0,
        0.0,
        0.0,
        0.001605615385050072,
        0.06828740321901541
      ],
      "mean": 0.0032595041232722217
    }
  }
]