[
  {
    "label": "Dabagh",
    "data": {
      "quartiles": [
        0.0,
        0.0,
        0.0,
        0.002998857070931411,
        0.05766486897772936
      ],
      "mean": 0.002787411704988669
    }
  },
  {
    "label": "Borda",
    "data": {
      "quartiles": [
        0.0,
        0.0,
        0.0,
        0.004243143313018685,
        0.07519367088666087
      ],
      "mean": 0.0034223535816578334
    }
  },
  {
    "label": "Bullet",
    "data": {
      "quartiles": [
        0.0,
        0.003825184050721884,
        0.009694889604438366,
        0.01853718192883186,
        0.09325521350699845
      ],
      "mean": 0.013001184151204041
    }
  },
  {
    "label": "Plurality",
    "data": {
      "quartiles": [
        0.0,
        0.0,
        0.0,
        0.002999010402464073,
        0.05507565777518209
      ],
      "mean": 0.0027847879781173874
    }
  },
  {
    "label": "Range (moving avg)",
    "data": {
      "quartiles": [
        0.0,
        0.0,
        0.0002864637705651418,
        0.004921119190206085,
        0.0520527091918563
      ],
      "mean": 0.003260261482495953
    }
  },
  {
    "label": "Range (threshold)",
    "data": {
      "quartiles": [
        0.0,
        0.0,
        0.0,
        0.003973044418499274,
        0.042086910927811444
      ],
      "mean": 0.002729761606097918
    }
  }
]