[
  {
    "label": "Dabagh",
    "data": {
      "quartiles": [
        0.0,
        0.0,
        0.004641894344805308,
        0.012010606647461088,
        0.043841449216567054
      ],
      "mean": 0.007121556348234793
    }
  },
  {
    "label": "Borda",
    "data": {
      "quartiles": [
        0.0,
        0.0,
        0.002470369385958726,
        0.009766167596347923,
        0.05025111618805212
      ],
      "mean": 0.005762052963922437
    }
  },
  {
    "label": "Bullet",
    "data": {
      "quartiles": [
        0.0,
        0.0013454176744525448,
        0.009761853414637221,
        0.018028480137417695,
        0.06275493614354566
      ],
      "mean": 0.011246394555682705
    }
  },
  {
    "label": "Plurality",
    "data": {
      "quartiles": [
        0.0,
        0.0,
        0.004381422980651877,
        0.011967270662190827,
        0.04907392037689924
      ],
      "mean": 0.007085283125461892
    }
  },
  {
    "label": "Range (moving avg)",
    "data": {
      "quartiles": [
        0.0,
        0.0,
        0.0,
        0.00433394285278867,
        0.03170671030258774
      ],
      "mean": 0.0027440983897469243
    }
  },
  {
    "label": "Range (threshold)",
    "data": {
      "quartiles": [
        0.0,
        0.0,
        0.0,
        0.0043168551673927165,
        0.03438218287336049
      ],
      "mean": 0.002756558934914784
    }
  }
]