[
  {
    "label": "Dabagh",
    "data": {
      "quartiles": [
        0.0,
        0.0,
        0.0,
        0.0030715844977426345,
        0.06358067617500751
      ],
      "mean": 0.003639159951530395
    }
  },
  {
    "label": "Borda",
    "data": {
      "quartiles": [
        0.0,
        0.0,
        0.0,
        0.007052528690008391,
        0.0875220576585928
      ],
      "mean": 0.005614169432268529
    }
  },
  {
    "label": "Bullet",
    "data": {
      "quartiles": [
        0.0,
        0.02257502256996531,
        0.035363497898694474,
        0.05061251380226407,
        0.13519001474950137
      ],
      "mean": 0.03799234517788641
    }
  },
  {
    "label": "Plurality",
    "data": {
      "quartiles": [
        0.0,
        0.0,
        0.0,
        0.005500476931663538,
        0.08228775040318397
      ],
      "mean": 0.004707775724605618
    }
  },
  {
    "label": "Approval",
    "data": {
      "quartiles": [
        0.0,
        0.0,
        0.0,
        0.0008640605775196697,
        0.04726865619239213
      ],
      "mean": 0.0026410409832809388
    }
  },
  {
    "label": "Range",
    "data": {
      "quartiles": [
        0.0,
        0.0,
        0.0,
        0.004173089583505209,
        0.05641507216916722
      ],
      "mean": 0.0038646352106494163
    }
  }
]