[
  {
    "label": "Star",
    "data": {
      "quartiles": [
        0.0,
        0.0,
        0.0,
        0.0015737328322323486,
        0.047074209890879855
      ],
      "mean": 0.0018047149520218644
    }
  },
  {
    "label": "Bucklin",
    "data": {
      "quartiles": [
        0.0,
        0.0,
        0.0,
        0.005747695292227046,
        0.06884484075910428
      ],
      "mean": 0.004118356939226883
    }
  },
  {
    "label": "Black",
    "data": {
      "quartiles": [
        0.0,
        0.0,
        0.0,
        0.0022642932092296064,
        0.05278092132191837
      ],
      "mean": 0.002418384300282012
    }
  },
  {
    "label": "Copeland",
    "data": {
      "quartiles": [
        0.0,
        0.0,
        0.0,
        0.0017244882950236118,
        0.050672454316956037
      ],
      "mean": 0.0020915751840580627
    }
  },
  {
    "label": "Ranked Choice Most Last",
    "data": {
      "quartiles": [
        0.0,
        0.004549021260272958,
        0.010132700497644899,
        0.017781551925717204,
        0.07684619513113652
      ],
      "mean": 0.01245244969154513
    }
  },
  {
    "label": "Ranked Choice Fewest First",
    "data": {
      "quartiles": [
        0.0,
        0.0,
        0.0,
        0.0,
        0.027311564460264462
      ],
      "mean": 0.0007171504897883514
    }
  },
  {
    "label": "Condorcet Ranked Pairs",
    "data": {
      "quartiles": [
        0.0,
        0.0,
        0.0,
        0.0010720076251516807,
        0.041543607423954756
      ],
      "mean": 0.0017953927058048404
    }
  },
  {
    "label": "Condorcet Least Reversal",
    "data": {
      "quartiles": [
        0.0,
        0.0,
        0.0,
        0.001139060872164297,
        0.05121231015584165
      ],
      "mean": 0.001859830045763654
    }
  },
  {
    "label": "Plurality + runoff",
    "data": {
      "quartiles": [
        0.0,
        0.0,
        0.0,
        0.0,
        0.02743435261113845
      ],
      "mean": 0.0006936409025537564
    }
  }
]