[
  {
    "label": "Star",
    "data": {
      "quartiles": [
        0.0,
        0.0,
        0.0,
        0.0009224803697922646,
        0.03696020386667719
      ],
      "mean": 0.001544610303173451
    }
  },
  {
    "label": "Bucklin",
    "data": {
      "quartiles": [
        0.0,
        0.0,
        0.0,
        0.0005336829760529227,
        0.05956787408327756
      ],
      "mean": 0.0017510637841608456
    }
  },
  {
    "label": "Black",
    "data": {
      "quartiles": [
        0.0,
        0.0,
        0.0,
        0.0008942355390685108,
        0.06994321675942579
      ],
      "mean": 0.0019187436217855496
    }
  },
  {
    "label": "Copeland",
    "data": {
      "quartiles": [
        0.0,
        0.0,
        0.0,
        0.000568703229156462,
        0.05441897704711373
      ],
      "mean": 0.0016088125641902729
    }
  },
  {
    "label": "Single Transferable Most Last",
    "data": {
      "quartiles": [
        0.0,
        0.005302633313551989,
        0.010821455985980107,
        0.01841368066949025,
        0.08049307303440806
      ],
      "mean": 0.013227250370216239
    }
  },
  {
    "label": "Single Transferable Fewest First",
    "data": {
      "quartiles": [
        0.0,
        0.0,
        0.0,
        0.0,
        0.03466746932126753
      ],
      "mean": 0.000746987217703916
    }
  },
  {
    "label": "Condorcet Ranked Pairs",
    "data": {
      "quartiles": [
        0.0,
        0.0,
        0.0,
        0.00008113913047600008,
        0.04776899535832776
      ],
      "mean": 0.0011142017842642573
    }
  },
  {
    "label": "Condorcet Least Reversal",
    "data": {
      "quartiles": [
        0.0,
        0.0,
        0.0,
        0.0,
        0.04266822037819168
      ],
      "mean": 0.0010893934533450869
    }
  },
  {
    "label": "Plurality + runoff",
    "data": {
      "quartiles": [
        0.0,
        0.0,
        0.0,
        0.0,
        0.028784139213051885
      ],
      "mean": 0.0007465669970198099
    }
  }
]